gazehound
