Metadata-Version: 1.0
Name: gazehound
Version: 0.2.2
Summary: Utilities for viewing and analyzing gaze tracking (and eyetracking) data
Home-page: http://github.com/njvack/gazehound
Author: Nathan Vack
Author-email: njvack@wisc.edu
License: GPL 2.0
Keywords: gazetracking eyetracking psychology science research
Platform: UNKNOWN
Classifier: Development Status :: 2 - Pre-Alpha
Classifier: Environment :: Console
Classifier: Environment :: Web Environment
Classifier: Intended Audience :: Developers
Classifier: Intended Audience :: Science/Research
Classifier: License :: OSI Approved :: GNU General Public License (GPL)
Classifier: Natural Language :: English
Classifier: Operating System :: OS Independent
Classifier: Programming Language :: Python
Classifier: Topic :: Scientific/Engineering :: Information Analysis
